dedeucerl/__init__.py
dedeucerl/vf_env.py
dedeucerl/adapters/__init__.py
dedeucerl/adapters/anthropic.py
dedeucerl/adapters/base.py
dedeucerl/adapters/gemini.py
dedeucerl/adapters/heuristic.py
dedeucerl/adapters/openai.py
dedeucerl/cli/__init__.py
dedeucerl/cli/aggregate.py
dedeucerl/cli/eval.py
dedeucerl/cli/eval_parallel.py
dedeucerl/cli/generate.py
dedeucerl/cli/selfcheck.py
dedeucerl/cli/train.py
dedeucerl/core/__init__.py
dedeucerl/core/automata.py
dedeucerl/core/config.py
dedeucerl/core/domain_spec.py
dedeucerl/core/env.py
dedeucerl/core/rubric.py
dedeucerl/core/task_generator.py
dedeucerl/core/types.py
dedeucerl/skins/__init__.py
dedeucerl/skins/_template.py
dedeucerl/skins/apienv.py
dedeucerl/skins/exprpolicy.py
dedeucerl/skins/mealy.py
dedeucerl/skins/protocol.py
dedeucerl/utils/__init__.py
dedeucerl/utils/episodes.py
dedeucerl/utils/errors.py
dedeucerl/utils/logging.py
dedeucerl/utils/rng.py
dedeucerl/utils/schema.py
dedeucerl-1.0.6.dist-info/licenses/LICENSE
dedeucerl-1.0.6.dist-info/METADATA
dedeucerl-1.0.6.dist-info/WHEEL
dedeucerl-1.0.6.dist-info/entry_points.txt
dedeucerl-1.0.6.dist-info/top_level.txt
dedeucerl-1.0.6.dist-info/RECORD
