Metadata-Version: 2.4
Name: dedeucerl
Version: 1.0.6
Summary: A modular framework for active system identification benchmarks
Author: Vedansh
License: MIT License
Project-URL: Homepage, https://github.com/AashVed/DedeuceRL
Project-URL: Repository, https://github.com/AashVed/DedeuceRL
Project-URL: Issues, https://github.com/AashVed/DedeuceRL/issues
Keywords: reinforcement-learning,llm,benchmarks,evaluation,active-learning,system-identification,mealy-machines,api-testing
Classifier: Development Status :: 4 - Beta
Classifier: Intended Audience :: Developers
Classifier: Intended Audience :: Science/Research
Classifier: License :: OSI Approved :: MIT License
Classifier: Programming Language :: Python :: 3
Classifier: Programming Language :: Python :: 3.10
Classifier: Programming Language :: Python :: 3.11
Classifier: Programming Language :: Python :: 3.12
Classifier: Topic :: Scientific/Engineering :: Artificial Intelligence
Requires-Python: >=3.10
License-File: LICENSE
Requires-Dist: verifiers>=0.1.9
Requires-Dist: datasets>=2.0
Provides-Extra: openai
Requires-Dist: openai>=1.0; extra == "openai"
Provides-Extra: anthropic
Requires-Dist: anthropic>=0.20; extra == "anthropic"
Provides-Extra: gemini
Requires-Dist: google-genai>=0.1; extra == "gemini"
Provides-Extra: all
Requires-Dist: openai>=1.0; extra == "all"
Requires-Dist: anthropic>=0.20; extra == "all"
Requires-Dist: google-genai>=0.1; extra == "all"
Provides-Extra: dev
Requires-Dist: pytest>=7.0; extra == "dev"
Requires-Dist: pytest-asyncio>=0.21; extra == "dev"
Requires-Dist: ruff>=0.1; extra == "dev"
Provides-Extra: rl
Requires-Dist: verifiers[rl]>=0.1.9; extra == "rl"
Dynamic: license-file
